motionless/__init__.py
motionless/gpolyencode.py
motionless-1.3.3.dist-info/LICENSE
motionless-1.3.3.dist-info/METADATA
motionless-1.3.3.dist-info/WHEEL
motionless-1.3.3.dist-info/top_level.txt
motionless-1.3.3.dist-info/RECORD
