Metadata-Version: 2.1
Name: motionless
Version: 1.3.3
Summary: An easy way to generate Google Static Map URLs with Python.
Home-page: http://github.com/ryancox/motionless
Author: Ryan Cox
Author-email: ryan.a.cox@gmail.com
License: Apache 2.0 License
Keywords: google static maps url api georss mapping gpx kml geo gis
Platform: UNKNOWN
Classifier: Development Status :: 4 - Beta
Classifier: Intended Audience :: Developers
Classifier: License :: OSI Approved :: Apache Software License
Classifier: Topic :: Software Development :: Libraries :: Python Modules
Classifier: Topic :: Internet :: WWW/HTTP :: Dynamic Content
Classifier: Topic :: Multimedia :: Graphics :: Presentation
Classifier: Topic :: Internet
Classifier: Programming Language :: Python :: 2
Classifier: Programming Language :: Python :: 2.7
Classifier: Programming Language :: Python :: 3
Classifier: Programming Language :: Python :: 3.4
Classifier: Programming Language :: Python :: 3.5
Requires-Dist: setuptools
